talemai/__init__.py
talemai/__main__.py
talemai/helper/creditionals.py
talemai/helper/pdf.py
talemai/helper/spinner.py
talemai/helper/store_vectors.py
talemai/helper/__pycache__/creditionals.cpython-312.pyc
talemai/helper/__pycache__/pdf.cpython-312.pyc
talemai/helper/__pycache__/spinner.cpython-312.pyc
talemai/helper/__pycache__/store_vectors.cpython-312.pyc
talemai-0.4.0.dist-info/METADATA
talemai-0.4.0.dist-info/WHEEL
talemai-0.4.0.dist-info/entry_points.txt
talemai-0.4.0.dist-info/top_level.txt
talemai-0.4.0.dist-info/RECORD
