Metadata-Version: 2.1
Name: talemai
Version: 0.4.0
Summary: A description of your project
Author: Hemit Patel
Requires-Python: >=3.8
Requires-Dist: click
Requires-Dist: aiofiles
Requires-Dist: PyPDF2
Requires-Dist: pypdf
Requires-Dist: pyfiglet
Requires-Dist: langchain
Requires-Dist: langchain-community
Requires-Dist: langchain-astradb
Requires-Dist: langchain-huggingface
